[
    {
        "Id": 1,
        "Nombre": "Eugenio Luna",
        "Direccion": " 03(124)806-0594",
        "Telefono": " 672 Gwen Rapids Suite 184"
    },
    {
        "Id": 2,
        "Nombre": "Rosalia Bustos",
        "Direccion": " 617(11)469-8075",
        "Telefono": " 3300 Simonis Forge Suite 456"
    },
    {
        "Id": 3,
        "Nombre": "Carolina Mendoza",
        "Direccion": " 2(587)237-3989",
        "Telefono": " 44827 Micheal Stream Apt. 592"
    },
    {
        "Id": 4,
        "Nombre": "Jesus Manuel Diaz",
        "Direccion": " 64(9431)174-57-00",
        "Telefono": " 4884 Van Stravenue Apt. 642"
    },
    {
        "Id": 5,
        "Nombre": "Juan Francisco Rodr\u00EDguez",
        "Direccion": " 502(89)827-90-98",
        "Telefono": " 013 Price Stravenue Apt. 330"
    },
    {
        "Id": 6,
        "Nombre": "Julia Neira",
        "Direccion": " 523(62)857-30-65",
        "Telefono": " 768 Jamal Lake Suite 611"
    },
    {
        "Id": 7,
        "Nombre": "Mariona Real",
        "Direccion": " 954(879)351-72-84",
        "Telefono": " 7835 Bella Court Apt. 641"
    },
    {
        "Id": 8,
        "Nombre": "Yesica Torregrosa",
        "Direccion": " 68(538)135-55-91",
        "Telefono": " 043 Westley Plaza Apt. 180"
    },
    {
        "Id": 9,
        "Nombre": "Neus San Juan",
        "Direccion": " 87(23)651-47-76",
        "Telefono": " 2216 Kiehn Drives Suite 820"
    },
    {
        "Id": 10,
        "Nombre": "Jose Andres Alvaro",
        "Direccion": " 228(268)331-46-19",
        "Telefono": " 787 Schaden Garden Apt. 820"
    },
    {
        "Id": 11,
        "Nombre": "Elsa Amaya",
        "Direccion": " 576(9457)207-16-26",
        "Telefono": " 27977 Blanda Circles Suite 378"
    },
    {
        "Id": 12,
        "Nombre": "Ruben Cabezas",
        "Direccion": " 20(929)317-57-02",
        "Telefono": " 299 Madisyn Squares Apt. 671"
    },
    {
        "Id": 13,
        "Nombre": "Alex Quesada",
        "Direccion": " 254(2277)962-39-54",
        "Telefono": " 9303 Carroll Lakes Suite 390"
    },
    {
        "Id": 14,
        "Nombre": "Hector Silva",
        "Direccion": " 4(5162)912-91-52",
        "Telefono": " 9314 Dorthy Junctions Apt. 934"
    },
    {
        "Id": 15,
        "Nombre": "Martin Cordoba",
        "Direccion": " 62(4771)629-43-23",
        "Telefono": " 9106 Dorcas Key Apt. 517"
    },
    {
        "Id": 16,
        "Nombre": "Eulalia Montero",
        "Direccion": " 4(686)298-09-33",
        "Telefono": " 716 Vandervort Summit Suite 938"
    },
    {
        "Id": 17,
        "Nombre": "Chloe Corral",
        "Direccion": " 074(67)148-13-87",
        "Telefono": " 5588 Schuster Field Apt. 074"
    },
    {
        "Id": 18,
        "Nombre": "Gisela Pino",
        "Direccion": " 564(254)670-43-63",
        "Telefono": " 994 Jeanie Union Suite 895"
    },
    {
        "Id": 19,
        "Nombre": "Fernando Marquez",
        "Direccion": " 643(993)469-09-06",
        "Telefono": " 1035 Golden Mountain Suite 999"
    },
    {
        "Id": 20,
        "Nombre": "Raimundo Montoya",
        "Direccion": " 05(5960)913-88-55",
        "Telefono": " 111 Shemar Drives Apt. 223"
    },
    {
        "Id": 21,
        "Nombre": "Flora Echevarria",
        "Direccion": " 9(945)853-16-20",
        "Telefono": " 585 Ullrich Loaf Suite 422"
    },
    {
        "Id": 22,
        "Nombre": "Josep Sans",
        "Direccion": " 35(750)039-62-60",
        "Telefono": " 819 Glenna Brooks Suite 501"
    },
    {
        "Id": 23,
        "Nombre": "Ildefonso Lopez",
        "Direccion": " 4(5073)520-99-97",
        "Telefono": " 562 Macejkovic Harbor Apt. 402"
    },
    {
        "Id": 24,
        "Nombre": "Carla Arranz",
        "Direccion": " 37(3065)376-87-37",
        "Telefono": " 814 Bogisich Knoll Apt. 059"
    },
    {
        "Id": 25,
        "Nombre": "Norberto Vives",
        "Direccion": " 401(587)781-46-87",
        "Telefono": " 00708 Karley Spring Suite 124"
    },
    {
        "Id": 26,
        "Nombre": "Unai Nieves",
        "Direccion": " 394(3027)472-14-07",
        "Telefono": " 2469 Marilie Centers Apt. 914"
    },
    {
        "Id": 27,
        "Nombre": "Gustavo Gonzalo",
        "Direccion": " 44(294)439-11-67",
        "Telefono": " 9796 Leffler Row Suite 063"
    },
    {
        "Id": 28,
        "Nombre": "Sacramento Rivero",
        "Direccion": " 6(453)110-07-78",
        "Telefono": " 205 Jeffrey Pike Suite 096"
    },
    {
        "Id": 29,
        "Nombre": "Ruth Perales",
        "Direccion": " 758(4144)278-76-57",
        "Telefono": " 21131 Koepp Knoll Suite 316"
    },
    {
        "Id": 30,
        "Nombre": "Florencio Nieves",
        "Direccion": " 8(86)687-96-67",
        "Telefono": " 09105 Bailey Forge Apt. 999"
    },
    {
        "Id": 31,
        "Nombre": "Ayman Saez",
        "Direccion": " 9(2797)294-97-05",
        "Telefono": " 73991 Wisozk Plains Suite 382"
    },
    {
        "Id": 32,
        "Nombre": "Cecilio del Campo",
        "Direccion": " 286(7771)389-81-08",
        "Telefono": " 465 Nader Crossroad Apt. 381"
    },
    {
        "Id": 33,
        "Nombre": "Cesar Amat",
        "Direccion": " 980(70)921-76-85",
        "Telefono": " 757 Nadia Views Apt. 012"
    },
    {
        "Id": 34,
        "Nombre": "Victor Manuel Fuster",
        "Direccion": " 943(4919)057-15-21",
        "Telefono": " 405 Frami Pike Apt. 086"
    },
    {
        "Id": 35,
        "Nombre": "Coral Vives",
        "Direccion": " 67(38)221-67-47",
        "Telefono": " 4867 Becker Corner Apt. 506"
    },
    {
        "Id": 36,
        "Nombre": "Gracia Valverde",
        "Direccion": " 65(0625)953-19-59",
        "Telefono": " 96482 Mallory Summit Suite 870"
    },
    {
        "Id": 37,
        "Nombre": "Macarena Franco",
        "Direccion": " 07(719)313-53-19",
        "Telefono": " 203 Kyle Well Suite 770"
    },
    {
        "Id": 38,
        "Nombre": "Enriqueta Ruano",
        "Direccion": " 53(024)708-13-28",
        "Telefono": " 21145 Annabel Mills Suite 883"
    },
    {
        "Id": 39,
        "Nombre": "Benito Aznar",
        "Direccion": " 917(22)132-28-32",
        "Telefono": " 1243 Berge Island Suite 040"
    },
    {
        "Id": 40,
        "Nombre": "Jose Manuel Roman",
        "Direccion": " 1(5807)604-33-61",
        "Telefono": " 84686 Block Port Suite 487"
    },
    {
        "Id": 41,
        "Nombre": "Guillermo Exposito",
        "Direccion": " 9(159)100-41-95",
        "Telefono": " 95950 Elmira Stream Suite 251"
    },
    {
        "Id": 42,
        "Nombre": "Amaia Acedo",
        "Direccion": " 70(55)073-18-32",
        "Telefono": " 89605 Emerald Flat Apt. 536"
    },
    {
        "Id": 43,
        "Nombre": "Marino Collado",
        "Direccion": " 5(761)319-10-13",
        "Telefono": " 225 Ortiz Camp Apt. 280"
    },
    {
        "Id": 44,
        "Nombre": "Celsa Acevedo",
        "Direccion": " 68(5041)110-11-50",
        "Telefono": " 4561 Madelynn Knolls Apt. 573"
    },
    {
        "Id": 45,
        "Nombre": "Yago Fernndez",
        "Direccion": " 904(054)087-82-23",
        "Telefono": " 71895 Kamille Greens Apt. 217"
    },
    {
        "Id": 46,
        "Nombre": "Hipolito Figueroa",
        "Direccion": " 50(86)308-45-42",
        "Telefono": " 7295 Halvorson Shoals Apt. 402"
    },
    {
        "Id": 47,
        "Nombre": "Isabel Lazaro",
        "Direccion": " 4(925)979-09-04",
        "Telefono": " 675 Marvin Alley Suite 969"
    },
    {
        "Id": 48,
        "Nombre": "Chloe Teruel",
        "Direccion": " 0(851)367-1699",
        "Telefono": " 5479 Devon Plains Suite 872"
    },
    {
        "Id": 49,
        "Nombre": "Juana Romera",
        "Direccion": " 48(07)892-5313",
        "Telefono": " 892 Steve Summit Suite 301"
    },
    {
        "Id": 50,
        "Nombre": "Emma Lin",
        "Direccion": " 265(375)801-8816",
        "Telefono": " 803 Bruen Isle Suite 693"
    },
    {
        "Id": 51,
        "Nombre": "Gonzalo Robinson",
        "Direccion": "La Rioja 3500",
        "Telefono": "3815799416"
    },
    {
        "Id": 52,
        "Nombre": "Lionel Messi",
        "Direccion": "Miami, EEUU",
        "Telefono": "545879101010"
    },
    {
        "Id": 53,
        "Nombre": "Cristiano Ronaldo",
        "Direccion": "Arabia Saudita",
        "Telefono": "7777777777"
    }
]